Metadata-Version: 1.1
Name: kickstart-avs
Version: 0.2.2
Summary: automate avs launch on raspberry pi
Home-page: https://github.com/PseudoAj/kickstart_avs
Author: Ajay Krishna Teja Kavuri
Author-email: ajaykrishnateja@gmail.com
License: MIT
Keywords: alexa avs raspberrypi startup launch
Platform: UNKNOWN
Classifier: Development Status :: 4 - Beta
Classifier: Programming Language :: Python :: 2.7
Classifier: Topic :: Scientific/Engineering :: Human Machine Interfaces
